{"run_number": "1744920701837273", "step_name": "load_model", "task_id": "3", "attempt_id": 0, "name": "model", "content_type": "gzip+pickle-v4", "type": "metaflow.artifact", "sha": "0bbe349e88613663822105690e9313c7c608f39a", "ds_type": "local", "location": ":root:/Users/jahnavipaliwal/Desktop/ML_Ops/MLOps/Labs/Lab6/.metaflow", "flow_id": "ScoringFlow", "user_name": "jahnavipaliwal", "tags": [], "system_tags": ["runtime:dev", "user:jahnavipaliwal", "metaflow_version:2.15.7", "python_version:3.12.9"], "ts_epoch": 1744920705332}